opendata/__init__.py
opendata/dataset.py
opendata/utils.py
opendata_kr-0.0.9.dist-info/LICENSE
opendata_kr-0.0.9.dist-info/METADATA
opendata_kr-0.0.9.dist-info/WHEEL
opendata_kr-0.0.9.dist-info/top_level.txt
opendata_kr-0.0.9.dist-info/RECORD
